CTkStarRating/__init__.py
CTkStarRating/ctk_star_rating.py
CTkStarRating/assets/empty_star.png
CTkStarRating/assets/full_star.png
CTkStarRating/assets/full_star_hover.png
CTkStarRating/assets/hover_star.png
CTkRatingStar-0.0.1.dist-info/LICENSE
CTkRatingStar-0.0.1.dist-info/METADATA
CTkRatingStar-0.0.1.dist-info/WHEEL
CTkRatingStar-0.0.1.dist-info/top_level.txt
CTkRatingStar-0.0.1.dist-info/RECORD
