Metadata-Version: 2.1
Name: CTkRatingStar
Version: 0.0.1
Summary: A customizable star rating widget for CustomTkinter applications.
Author-email: ZachVFX <zachallrd@gmail.com>
License: MIT License
Project-URL: Homepage, https://github.com/ZachVFXX/CtkRatingStar/tree/main
Project-URL: Issues, https://github.com/ZachVFXX/CtkRatingStar/issues
Keywords: customtkinter,star,rating,widget
Classifier: Programming Language :: Python :: 3
Classifier: License :: OSI Approved :: MIT License
Classifier: Operating System :: OS Independent
Requires-Python: >=3.8
License-File: LICENSE
Requires-Dist: customtkinter
Requires-Dist: pillow
